qkdisplays/__init__.py
qkdisplays/gtk.py
qkdisplays/main.py
qkdisplays/types.py
qkdisplays-1.0.dist-info/licenses/LICENSE
qkdisplays-1.0.dist-info/METADATA
qkdisplays-1.0.dist-info/WHEEL
qkdisplays-1.0.dist-info/entry_points.txt
qkdisplays-1.0.dist-info/top_level.txt
qkdisplays-1.0.dist-info/RECORD
