Metadata-Version: 2.4
Name: qkdisplays
Version: 1.0
Summary: A helper tool for quickly configuring a multi-monitor setup, built with tiled window managers in mind
Author: Tamir Zahavi-Brunner
License-Expression: GPL-3.0-or-later
Keywords: sway,displays,monitor,utility
Classifier: Programming Language :: Python :: 3
Classifier: Operating System :: POSIX :: Linux
Classifier: Topic :: Desktop Environment :: Window Managers
Classifier: Topic :: Utilities
Requires-Python: >=3.10
License-File: LICENSE
Requires-Dist: i3ipc
Requires-Dist: PyGObject
Provides-Extra: dev
Requires-Dist: pytest; extra == "dev"
Requires-Dist: ruff; extra == "dev"
Requires-Dist: pyright; extra == "dev"
Dynamic: license-file
